{
  "name": "Фокус с ковром на заборе",
  "icon": "minecraft:cyan_carpet",
  "category": "lexicon:tips_tricks",
  "pages": [
    {
      "type": "patchouli:text",
      "text": "$(item)Carpets$() на $(item)Fences$() имеют особое свойство: они позволяют вам легко перелезать через $(thing)Fence$(), но мешают животным и монстрам. $(br2)Это можно использовать для загонов и защитных ограждений."
    },
    {
      "type": "patchouli:image",
      "images": [
        "lexicon:textures/pictures/carpet_fence_trick.png"
      ],
      "border": true
    }
  ]
}
