{
  "name": "Nether Exploration",
  "icon": "minecraft:netherrack",
  "category": "lexicon:exploring",
  "sortnum": 3,
  "pages": [
    {
      "type": "patchouli:text",
      "text": "Here are some important items that you should always have with your adventure in the $(thing)Nether$()!"
    },
    {
      "type": "patchouli:image",
      "images": [
        "lexicon:textures/pictures/nether_equipment.png",
        "lexicon:textures/pictures/additional_equipment.png"
      ],
      "border": true
    }

  ]
}